{
  "forge_marker": 1,
  "defaults": {
    "model": "mcgproject:generated",
    "textures": {"layer0": "mcgproject:items/food/pic0"}
  },
  "variants": {
    "inventory": [{}],
    "normal": [{}],
    "0": [{"textures": {"layer0": "mcgproject:items/food/pic0"}}],
    "1": [{"textures": {"layer0": "mcgproject:items/food/pic1"}}],
    "2": [{"textures": {"layer0": "mcgproject:items/food/pic2"}}],
    "3": [{"textures": {"layer0": "mcgproject:items/food/pic3"}}],
    "4": [{"textures": {"layer0": "mcgproject:items/food/pic4"}}],
    "5": [{"textures": {"layer0": "mcgproject:items/food/pic5"}}],
    "6": [{"textures": {"layer0": "mcgproject:items/food/pic6"}}],
    "7": [{"textures": {"layer0": "mcgproject:items/food/pic7"}}],
    "8": [{"textures": {"layer0": "mcgproject:items/food/pic8"}}],
    "9": [{"textures": {"layer0": "mcgproject:items/food/pic9"}}],
    "10": [{"textures": {"layer0": "mcgproject:items/food/pic10"}}],
    "11": [{"textures": {"layer0": "mcgproject:items/food/pic11"}}],
    "12": [{"textures": {"layer0": "mcgproject:items/food/pic12"}}],
    "13": [{"textures": {"layer0": "mcgproject:items/food/pic13"}}],
    "14": [{"textures": {"layer0": "mcgproject:items/food/pic14"}}],
    "15": [{"textures": {"layer0": "mcgproject:items/food/pic15"}}],
    "16": [{"textures": {"layer0": "mcgproject:items/food/pic16"}}],
    "17": [{"textures": {"layer0": "mcgproject:items/food/pic17"}}],
    "18": [{"textures": {"layer0": "mcgproject:items/food/pic18"}}],
    "19": [{"textures": {"layer0": "mcgproject:items/food/pic19"}}],
    "20": [{"textures": {"layer0": "mcgproject:items/food/pic20"}}],
    "21": [{"textures": {"layer0": "mcgproject:items/food/pic21"}}],
    "22": [{"textures": {"layer0": "mcgproject:items/food/pic22"}}],
    "23": [{"textures": {"layer0": "mcgproject:items/food/pic23"}}],
    "24": [{"textures": {"layer0": "mcgproject:items/food/pic24"}}],
    "25": [{"textures": {"layer0": "mcgproject:items/food/pic25"}}],
    "26": [{"textures": {"layer0": "mcgproject:items/food/pic26"}}],
    "27": [{"textures": {"layer0": "mcgproject:items/food/pic27"}}],
    "28": [{"textures": {"layer0": "mcgproject:items/food/pic28"}}],
    "29": [{"textures": {"layer0": "mcgproject:items/food/pic29"}}],
    "30": [{"textures": {"layer0": "mcgproject:items/food/pic30"}}],
    "31": [{"textures": {"layer0": "mcgproject:items/food/pic31"}}],
    "32": [{"textures": {"layer0": "mcgproject:items/food/pic32"}}],
    "33": [{"textures": {"layer0": "mcgproject:items/food/pic33"}}],
    "34": [{"textures": {"layer0": "mcgproject:items/food/pic34"}}],
    "35": [{"textures": {"layer0": "mcgproject:items/food/pic35"}}],
    "36": [{"textures": {"layer0": "mcgproject:items/food/pic36"}}],
    "37": [{"textures": {"layer0": "mcgproject:items/food/pic37"}}],
    "38": [{"textures": {"layer0": "mcgproject:items/food/pic38"}}],
    "39": [{"textures": {"layer0": "mcgproject:items/food/pic39"}}],
    "40": [{"textures": {"layer0": "mcgproject:items/food/pic40"}}],
    "41": [{"textures": {"layer0": "mcgproject:items/food/pic41"}}],
    "42": [{"textures": {"layer0": "mcgproject:items/food/pic42"}}],
    "43": [{"textures": {"layer0": "mcgproject:items/food/pic43"}}],
    "44": [{"textures": {"layer0": "mcgproject:items/food/pic44"}}],
    "45": [{"textures": {"layer0": "mcgproject:items/food/pic45"}}],
    "46": [{"textures": {"layer0": "mcgproject:items/food/pic46"}}],
    "47": [{"textures": {"layer0": "mcgproject:items/food/pic47"}}],
    "48": [{"textures": {"layer0": "mcgproject:items/food/pic48"}}],
    "49": [{"textures": {"layer0": "mcgproject:items/food/pic49"}}],
    "50": [{"textures": {"layer0": "mcgproject:items/food/pic50"}}],
    "51": [{"textures": {"layer0": "mcgproject:items/food/pic51"}}],
    "52": [{"textures": {"layer0": "mcgproject:items/food/pic52"}}],
    "53": [{"textures": {"layer0": "mcgproject:items/food/pic53"}}],
    "54": [{"textures": {"layer0": "mcgproject:items/food/pic54"}}],
    "55": [{"textures": {"layer0": "mcgproject:items/food/pic55"}}],
    "56": [{"textures": {"layer0": "mcgproject:items/food/pic56"}}],
    "57": [{"textures": {"layer0": "mcgproject:items/food/pic57"}}],
    "58": [{"textures": {"layer0": "mcgproject:items/food/pic58"}}],
    "59": [{"textures": {"layer0": "mcgproject:items/food/pic59"}}],
    "60": [{"textures": {"layer0": "mcgproject:items/food/pic60"}}],
    "61": [{"textures": {"layer0": "mcgproject:items/food/pic61"}}],
    "62": [{"textures": {"layer0": "mcgproject:items/food/pic62"}}],
    "63": [{"textures": {"layer0": "mcgproject:items/food/pic63"}}],
    "64": [{"textures": {"layer0": "mcgproject:items/food/pic64"}}],
    "65": [{"textures": {"layer0": "mcgproject:items/food/pic65"}}],
    "66": [{"textures": {"layer0": "mcgproject:items/food/pic66"}}],
    "67": [{"textures": {"layer0": "mcgproject:items/food/pic67"}}],
    "68": [{"textures": {"layer0": "mcgproject:items/food/pic68"}}],
    "69": [{"textures": {"layer0": "mcgproject:items/food/pic69"}}],
    "70": [{"textures": {"layer0": "mcgproject:items/food/pic70"}}],
    "71": [{"textures": {"layer0": "mcgproject:items/food/pic71"}}],
    "72": [{"textures": {"layer0": "mcgproject:items/food/pic72"}}],
    "73": [{"textures": {"layer0": "mcgproject:items/food/pic73"}}],
    "74": [{"textures": {"layer0": "mcgproject:items/food/pic74"}}],
    "75": [{"textures": {"layer0": "mcgproject:items/food/pic75"}}],
    "76": [{"textures": {"layer0": "mcgproject:items/food/pic76"}}],
    "77": [{"textures": {"layer0": "mcgproject:items/food/pic77"}}],
    "78": [{"textures": {"layer0": "mcgproject:items/food/pic78"}}],
    "79": [{"textures": {"layer0": "mcgproject:items/food/pic79"}}],
    "80": [{"textures": {"layer0": "mcgproject:items/food/pic80"}}],
    "81": [{"textures": {"layer0": "mcgproject:items/food/pic81"}}],
    "82": [{"textures": {"layer0": "mcgproject:items/food/pic82"}}],
    "83": [{"textures": {"layer0": "mcgproject:items/food/pic83"}}],
    "84": [{"textures": {"layer0": "mcgproject:items/food/pic84"}}],
    "85": [{"textures": {"layer0": "mcgproject:items/food/pic85"}}],
    "86": [{"textures": {"layer0": "mcgproject:items/food/pic86"}}],
    "87": [{"textures": {"layer0": "mcgproject:items/food/pic87"}}],
    "88": [{"textures": {"layer0": "mcgproject:items/food/pic88"}}],
    "89": [{"textures": {"layer0": "mcgproject:items/food/pic89"}}],
    "90": [{"textures": {"layer0": "mcgproject:items/food/pic90"}}],
    "91": [{"textures": {"layer0": "mcgproject:items/food/pic91"}}],
    "92": [{"textures": {"layer0": "mcgproject:items/food/pic92"}}],
    "93": [{"textures": {"layer0": "mcgproject:items/food/pic93"}}],
    "94": [{"textures": {"layer0": "mcgproject:items/food/pic94"}}]
  }
}